{
  "nodes": [
    {
      "id": "scourses",
      "group": 1
    },
    {
      "id": "courses",
      "group": 1
    },
    {
      "id": "sourses",
      "group": 1
    },
    {
      "id": "scorses",
      "group": 1
    },
    {
      "id": "scouses",
      "group": 1
    },
    {
      "id": "scourse",
      "group": 1
    },
    {
      "id": "curses",
      "group": 2
    },
    {
      "id": "corses",
      "group": 2
    },
    {
      "id": "coures",
      "group": 2
    },
    {
      "id": "course",
      "group": 2
    },
    {
      "id": "cures",
      "group": 3
    },
    {
      "id": "curse",
      "group": 3
    },
    {
      "id": "ures",
      "group": 4
    },
    {
      "id": "cues",
      "group": 4
    },
    {
      "id": "curs",
      "group": 4
    },
    {
      "id": "cure",
      "group": 4
    },
    {
      "id": "coses",
      "group": 3
    },
    {
      "id": "cores",
      "group": 3
    },
    {
      "id": "corse",
      "group": 3
    },
    {
      "id": "oses",
      "group": 4
    },
    {
      "id": "coss",
      "group": 4
    },
    {
      "id": "cose",
      "group": 4
    },
    {
      "id": "ores",
      "group": 4
    },
    {
      "id": "cors",
      "group": 4
    },
    {
      "id": "core",
      "group": 4
    },
    {
      "id": "cours",
      "group": 3
    },
    {
      "id": "coure",
      "group": 3
    },
    {
      "id": "ours",
      "group": 4
    },
    {
      "id": "cour",
      "group": 4
    },
    {
      "id": "souses",
      "group": 2
    },
    {
      "id": "sourse",
      "group": 2
    },
    {
      "id": "suses",
      "group": 3
    },
    {
      "id": "souse",
      "group": 3
    },
    {
      "id": "uses",
      "group": 4
    },
    {
      "id": "sues",
      "group": 4
    },
    {
      "id": "suss",
      "group": 4
    },
    {
      "id": "sous",
      "group": 4
    },
    {
      "id": "sours",
      "group": 3
    },
    {
      "id": "sour",
      "group": 4
    },
    {
      "id": "scores",
      "group": 2
    },
    {
      "id": "scorse",
      "group": 2
    },
    {
      "id": "sores",
      "group": 3
    },
    {
      "id": "score",
      "group": 3
    },
    {
      "id": "sore",
      "group": 4
    },
    {
      "id": "scuses",
      "group": 2
    },
    {
      "id": "scouse",
      "group": 2
    },
    {
      "id": "scuse",
      "group": 3
    },
    {
      "id": "scours",
      "group": 2
    },
    {
      "id": "scurs",
      "group": 3
    },
    {
      "id": "scour",
      "group": 3
    },
    {
      "id": "scur",
      "group": 4
    }
  ],
  "links": [
    {
      "source": "scourses",
      "target": "courses",
      "value": 1
    },
    {
      "source": "scourses",
      "target": "sourses",
      "value": 1
    },
    {
      "source": "scourses",
      "target": "scorses",
      "value": 1
    },
    {
      "source": "scourses",
      "target": "scouses",
      "value": 1
    },
    {
      "source": "scourses",
      "target": "scourse",
      "value": 1
    },
    {
      "source": "courses",
      "target": "curses",
      "value": 1
    },
    {
      "source": "courses",
      "target": "corses",
      "value": 1
    },
    {
      "source": "courses",
      "target": "coures",
      "value": 1
    },
    {
      "source": "courses",
      "target": "course",
      "value": 1
    },
    {
      "source": "curses",
      "target": "cures",
      "value": 1
    },
    {
      "source": "curses",
      "target": "curse",
      "value": 1
    },
    {
      "source": "cures",
      "target": "ures",
      "value": 1
    },
    {
      "source": "cures",
      "target": "cues",
      "value": 1
    },
    {
      "source": "cures",
      "target": "curs",
      "value": 1
    },
    {
      "source": "cures",
      "target": "cure",
      "value": 1
    },
    {
      "source": "curse",
      "target": "cure",
      "value": 1
    },
    {
      "source": "curse",
      "target": "curs",
      "value": 1
    },
    {
      "source": "corses",
      "target": "coses",
      "value": 1
    },
    {
      "source": "corses",
      "target": "cores",
      "value": 1
    },
    {
      "source": "corses",
      "target": "corse",
      "value": 1
    },
    {
      "source": "coses",
      "target": "oses",
      "value": 1
    },
    {
      "source": "coses",
      "target": "coss",
      "value": 1
    },
    {
      "source": "coses",
      "target": "cose",
      "value": 1
    },
    {
      "source": "cores",
      "target": "ores",
      "value": 1
    },
    {
      "source": "cores",
      "target": "cors",
      "value": 1
    },
    {
      "source": "cores",
      "target": "core",
      "value": 1
    },
    {
      "source": "corse",
      "target": "cose",
      "value": 1
    },
    {
      "source": "corse",
      "target": "core",
      "value": 1
    },
    {
      "source": "corse",
      "target": "cors",
      "value": 1
    },
    {
      "source": "coures",
      "target": "cures",
      "value": 1
    },
    {
      "source": "coures",
      "target": "cores",
      "value": 1
    },
    {
      "source": "coures",
      "target": "cours",
      "value": 1
    },
    {
      "source": "coures",
      "target": "coure",
      "value": 1
    },
    {
      "source": "cours",
      "target": "ours",
      "value": 1
    },
    {
      "source": "cours",
      "target": "curs",
      "value": 1
    },
    {
      "source": "cours",
      "target": "cors",
      "value": 1
    },
    {
      "source": "cours",
      "target": "cour",
      "value": 1
    },
    {
      "source": "coure",
      "target": "cure",
      "value": 1
    },
    {
      "source": "coure",
      "target": "core",
      "value": 1
    },
    {
      "source": "coure",
      "target": "cour",
      "value": 1
    },
    {
      "source": "course",
      "target": "curse",
      "value": 1
    },
    {
      "source": "course",
      "target": "corse",
      "value": 1
    },
    {
      "source": "course",
      "target": "coure",
      "value": 1
    },
    {
      "source": "course",
      "target": "cours",
      "value": 1
    },
    {
      "source": "sourses",
      "target": "souses",
      "value": 1
    },
    {
      "source": "sourses",
      "target": "sourse",
      "value": 1
    },
    {
      "source": "souses",
      "target": "suses",
      "value": 1
    },
    {
      "source": "souses",
      "target": "souse",
      "value": 1
    },
    {
      "source": "suses",
      "target": "uses",
      "value": 1
    },
    {
      "source": "suses",
      "target": "sues",
      "value": 1
    },
    {
      "source": "suses",
      "target": "suss",
      "value": 1
    },
    {
      "source": "souse",
      "target": "sous",
      "value": 1
    },
    {
      "source": "sourse",
      "target": "souse",
      "value": 1
    },
    {
      "source": "sourse",
      "target": "sours",
      "value": 1
    },
    {
      "source": "sours",
      "target": "ours",
      "value": 1
    },
    {
      "source": "sours",
      "target": "sous",
      "value": 1
    },
    {
      "source": "sours",
      "target": "sour",
      "value": 1
    },
    {
      "source": "scorses",
      "target": "corses",
      "value": 1
    },
    {
      "source": "scorses",
      "target": "scores",
      "value": 1
    },
    {
      "source": "scorses",
      "target": "scorse",
      "value": 1
    },
    {
      "source": "scores",
      "target": "cores",
      "value": 1
    },
    {
      "source": "scores",
      "target": "sores",
      "value": 1
    },
    {
      "source": "scores",
      "target": "score",
      "value": 1
    },
    {
      "source": "sores",
      "target": "ores",
      "value": 1
    },
    {
      "source": "sores",
      "target": "sore",
      "value": 1
    },
    {
      "source": "score",
      "target": "core",
      "value": 1
    },
    {
      "source": "score",
      "target": "sore",
      "value": 1
    },
    {
      "source": "scorse",
      "target": "corse",
      "value": 1
    },
    {
      "source": "scorse",
      "target": "score",
      "value": 1
    },
    {
      "source": "scouses",
      "target": "souses",
      "value": 1
    },
    {
      "source": "scouses",
      "target": "scuses",
      "value": 1
    },
    {
      "source": "scouses",
      "target": "scouse",
      "value": 1
    },
    {
      "source": "scuses",
      "target": "suses",
      "value": 1
    },
    {
      "source": "scuses",
      "target": "scuse",
      "value": 1
    },
    {
      "source": "scouse",
      "target": "souse",
      "value": 1
    },
    {
      "source": "scouse",
      "target": "scuse",
      "value": 1
    },
    {
      "source": "scourse",
      "target": "course",
      "value": 1
    },
    {
      "source": "scourse",
      "target": "sourse",
      "value": 1
    },
    {
      "source": "scourse",
      "target": "scorse",
      "value": 1
    },
    {
      "source": "scourse",
      "target": "scouse",
      "value": 1
    },
    {
      "source": "scourse",
      "target": "scours",
      "value": 1
    },
    {
      "source": "scours",
      "target": "cours",
      "value": 1
    },
    {
      "source": "scours",
      "target": "sours",
      "value": 1
    },
    {
      "source": "scours",
      "target": "scurs",
      "value": 1
    },
    {
      "source": "scours",
      "target": "scour",
      "value": 1
    },
    {
      "source": "scurs",
      "target": "curs",
      "value": 1
    },
    {
      "source": "scurs",
      "target": "scur",
      "value": 1
    },
    {
      "source": "scour",
      "target": "cour",
      "value": 1
    },
    {
      "source": "scour",
      "target": "sour",
      "value": 1
    },
    {
      "source": "scour",
      "target": "scur",
      "value": 1
    }
  ]
}