<?xml version="1.0"?>
<WordOutput xmlns:xsi="http://www.w3.org/2001/XMLSchema-instance" xmlns:xsd="http://www.w3.org/2001/XMLSchema">
  <nodes>
    <WordNode>
      <id>antaphrodisiacs</id>
      <Group>0</Group>
    </WordNode>
    <WordNode>
      <id>anaphrodisiacs</id>
    </WordNode>
    <WordNode>
      <id>antaphrodisiac</id>
    </WordNode>
    <WordNode>
      <id>anaphrodisias</id>
    </WordNode>
    <WordNode>
      <id>anaphrodisiac</id>
    </WordNode>
    <WordNode>
      <id>anaphrodisia</id>
    </WordNode>
    <WordNode>
      <id>antiaphrodisiac</id>
      <Group>0</Group>
    </WordNode>
    <WordNode>
      <id>antihelminthics</id>
      <Group>1</Group>
    </WordNode>
    <WordNode>
      <id>anthelminthics</id>
    </WordNode>
    <WordNode>
      <id>antihelminthic</id>
    </WordNode>
    <WordNode>
      <id>anthelmintics</id>
    </WordNode>
    <WordNode>
      <id>anthelminthic</id>
    </WordNode>
    <WordNode>
      <id>anthelmintic</id>
    </WordNode>
    <WordNode>
      <id>chemoautotrophs</id>
      <Group>2</Group>
    </WordNode>
    <WordNode>
      <id>chemautotrophs</id>
    </WordNode>
    <WordNode>
      <id>chemoautotroph</id>
    </WordNode>
    <WordNode>
      <id>chemautotroph</id>
    </WordNode>
    <WordNode>
      <id>chemoautotrophy</id>
      <Group>2</Group>
    </WordNode>
    <WordNode>
      <id>anaesthetically</id>
      <Group>3</Group>
    </WordNode>
    <WordNode>
      <id>anesthetically</id>
    </WordNode>
    <WordNode>
      <id>aesthetically</id>
    </WordNode>
    <WordNode>
      <id>esthetically</id>
    </WordNode>
    <WordNode>
      <id>beautifications</id>
      <Group>4</Group>
    </WordNode>
    <WordNode>
      <id>beatifications</id>
    </WordNode>
    <WordNode>
      <id>beautification</id>
    </WordNode>
    <WordNode>
      <id>beatification</id>
    </WordNode>
    <WordNode>
      <id>bougainvillaeas</id>
      <Group>5</Group>
    </WordNode>
    <WordNode>
      <id>bougainvilleas</id>
    </WordNode>
    <WordNode>
      <id>bougainvillaea</id>
    </WordNode>
    <WordNode>
      <id>bougainvillea</id>
    </WordNode>
    <WordNode>
      <id>canthaxanthines</id>
      <Group>6</Group>
    </WordNode>
    <WordNode>
      <id>canthaxanthins</id>
    </WordNode>
    <WordNode>
      <id>canthaxanthine</id>
    </WordNode>
    <WordNode>
      <id>canthaxanthin</id>
    </WordNode>
    <WordNode>
      <id>cercopithecoids</id>
      <Group>7</Group>
    </WordNode>
    <WordNode>
      <id>cercopithecids</id>
    </WordNode>
    <WordNode>
      <id>cercopithecoid</id>
    </WordNode>
    <WordNode>
      <id>cercopithecid</id>
    </WordNode>
    <WordNode>
      <id>conceptualisers</id>
      <Group>8</Group>
    </WordNode>
    <WordNode>
      <id>conceptualises</id>
    </WordNode>
    <WordNode>
      <id>conceptualiser</id>
    </WordNode>
    <WordNode>
      <id>conceptualise</id>
    </WordNode>
    <WordNode>
      <id>adiathermancies</id>
      <Group>9</Group>
    </WordNode>
    <WordNode>
      <id>diathermancies</id>
    </WordNode>
    <WordNode>
      <id>diathermacies</id>
    </WordNode>
  </nodes>
  <links>
    <WordEdge>
      <source>antaphrodisiacs</source>
      <target>anaphrodisiacs</target>
    </WordEdge>
    <WordEdge>
      <source>antaphrodisiacs</source>
      <target>antaphrodisiac</target>
    </WordEdge>
    <WordEdge>
      <source>anaphrodisiacs</source>
      <target>anaphrodisias</target>
    </WordEdge>
    <WordEdge>
      <source>anaphrodisiacs</source>
      <target>anaphrodisiac</target>
    </WordEdge>
    <WordEdge>
      <source>anaphrodisias</source>
      <target>anaphrodisia</target>
    </WordEdge>
    <WordEdge>
      <source>anaphrodisiac</source>
      <target>anaphrodisia</target>
    </WordEdge>
    <WordEdge>
      <source>antaphrodisiac</source>
      <target>anaphrodisiac</target>
    </WordEdge>
    <WordEdge>
      <source>antiaphrodisiac</source>
      <target>antaphrodisiac</target>
    </WordEdge>
    <WordEdge>
      <source>antihelminthics</source>
      <target>anthelminthics</target>
    </WordEdge>
    <WordEdge>
      <source>antihelminthics</source>
      <target>antihelminthic</target>
    </WordEdge>
    <WordEdge>
      <source>anthelminthics</source>
      <target>anthelmintics</target>
    </WordEdge>
    <WordEdge>
      <source>anthelminthics</source>
      <target>anthelminthic</target>
    </WordEdge>
    <WordEdge>
      <source>anthelmintics</source>
      <target>anthelmintic</target>
    </WordEdge>
    <WordEdge>
      <source>anthelminthic</source>
      <target>anthelmintic</target>
    </WordEdge>
    <WordEdge>
      <source>antihelminthic</source>
      <target>anthelminthic</target>
    </WordEdge>
    <WordEdge>
      <source>chemoautotrophs</source>
      <target>chemautotrophs</target>
    </WordEdge>
    <WordEdge>
      <source>chemoautotrophs</source>
      <target>chemoautotroph</target>
    </WordEdge>
    <WordEdge>
      <source>chemautotrophs</source>
      <target>chemautotroph</target>
    </WordEdge>
    <WordEdge>
      <source>chemoautotroph</source>
      <target>chemautotroph</target>
    </WordEdge>
    <WordEdge>
      <source>chemoautotrophy</source>
      <target>chemoautotroph</target>
    </WordEdge>
    <WordEdge>
      <source>anaesthetically</source>
      <target>anesthetically</target>
    </WordEdge>
    <WordEdge>
      <source>anesthetically</source>
      <target>aesthetically</target>
    </WordEdge>
    <WordEdge>
      <source>aesthetically</source>
      <target>esthetically</target>
    </WordEdge>
    <WordEdge>
      <source>beautifications</source>
      <target>beatifications</target>
    </WordEdge>
    <WordEdge>
      <source>beautifications</source>
      <target>beautification</target>
    </WordEdge>
    <WordEdge>
      <source>beatifications</source>
      <target>beatification</target>
    </WordEdge>
    <WordEdge>
      <source>beautification</source>
      <target>beatification</target>
    </WordEdge>
    <WordEdge>
      <source>bougainvillaeas</source>
      <target>bougainvilleas</target>
    </WordEdge>
    <WordEdge>
      <source>bougainvillaeas</source>
      <target>bougainvillaea</target>
    </WordEdge>
    <WordEdge>
      <source>bougainvilleas</source>
      <target>bougainvillea</target>
    </WordEdge>
    <WordEdge>
      <source>bougainvillaea</source>
      <target>bougainvillea</target>
    </WordEdge>
    <WordEdge>
      <source>canthaxanthines</source>
      <target>canthaxanthins</target>
    </WordEdge>
    <WordEdge>
      <source>canthaxanthines</source>
      <target>canthaxanthine</target>
    </WordEdge>
    <WordEdge>
      <source>canthaxanthins</source>
      <target>canthaxanthin</target>
    </WordEdge>
    <WordEdge>
      <source>canthaxanthine</source>
      <target>canthaxanthin</target>
    </WordEdge>
    <WordEdge>
      <source>cercopithecoids</source>
      <target>cercopithecids</target>
    </WordEdge>
    <WordEdge>
      <source>cercopithecoids</source>
      <target>cercopithecoid</target>
    </WordEdge>
    <WordEdge>
      <source>cercopithecids</source>
      <target>cercopithecid</target>
    </WordEdge>
    <WordEdge>
      <source>cercopithecoid</source>
      <target>cercopithecid</target>
    </WordEdge>
    <WordEdge>
      <source>conceptualisers</source>
      <target>conceptualises</target>
    </WordEdge>
    <WordEdge>
      <source>conceptualisers</source>
      <target>conceptualiser</target>
    </WordEdge>
    <WordEdge>
      <source>conceptualises</source>
      <target>conceptualise</target>
    </WordEdge>
    <WordEdge>
      <source>conceptualiser</source>
      <target>conceptualise</target>
    </WordEdge>
    <WordEdge>
      <source>adiathermancies</source>
      <target>diathermancies</target>
    </WordEdge>
    <WordEdge>
      <source>diathermancies</source>
      <target>diathermacies</target>
    </WordEdge>
  </links>
</WordOutput>